stellium/__init__.py
stellium/analysis/__init__.py
stellium/analysis/batch.py
stellium/analysis/export.py
stellium/analysis/frames.py
stellium/analysis/queries.py
stellium/analysis/stats.py
stellium/analysis/vector.py
stellium/chinese/__init__.py
stellium/chinese/calendar.py
stellium/chinese/core.py
stellium/chinese/protocols.py
stellium/chinese/bazi/__init__.py
stellium/chinese/bazi/analysis.py
stellium/chinese/bazi/engine.py
stellium/chinese/bazi/models.py
stellium/chinese/bazi/renderers.py
stellium/chinese/ziwei/__init__.py
stellium/cli/__init__.py
stellium/cli/cache.py
stellium/cli/chart.py
stellium/cli/ephemeris.py
stellium/cli/ephemeris_download.py
stellium/components/__init__.py
stellium/components/antiscia.py
stellium/components/arabic_parts.py
stellium/components/dignity.py
stellium/components/fixed_stars.py
stellium/components/midpoints.py
stellium/core/__init__.py
stellium/core/ayanamsa.py
stellium/core/builder.py
stellium/core/chart_utils.py
stellium/core/comparison.py
stellium/core/config.py
stellium/core/models.py
stellium/core/multichart.py
stellium/core/multiwheel.py
stellium/core/native.py
stellium/core/protocols.py
stellium/core/registry.py
stellium/core/synthesis.py
stellium/data/__init__.py
stellium/data/paths.py
stellium/data/registry.py
stellium/data/notables/INDEX.md
stellium/data/notables/generate_index.py
stellium/data/notables/births/architects.yaml
stellium/data/notables/births/artists.yaml
stellium/data/notables/births/astrologers.yaml
stellium/data/notables/births/athletes.yaml
stellium/data/notables/births/business.yaml
stellium/data/notables/births/criminals.yaml
stellium/data/notables/births/explorers.yaml
stellium/data/notables/births/leaders.yaml
stellium/data/notables/births/media.yaml
stellium/data/notables/births/occultists.yaml
stellium/data/notables/births/philosophers.yaml
stellium/data/notables/births/polymaths.yml
stellium/data/notables/births/scientists.yaml
stellium/data/notables/births/writers.yaml
stellium-0.15.1.dist-info/licenses/LICENSE
stellium-0.15.1.dist-info/METADATA
stellium-0.15.1.dist-info/WHEEL
stellium-0.15.1.dist-info/entry_points.txt
stellium-0.15.1.dist-info/top_level.txt
stellium-0.15.1.dist-info/RECORD
